cdk_gitlab_runner/__init__.py
cdk_gitlab_runner/py.typed
cdk_gitlab_runner/_jsii/__init__.py
cdk_gitlab_runner/_jsii/cdk-gitlab-runner@2.3.358.jsii.tgz
cdk_gitlab_runner-2.3.358.dist-info/LICENSE
cdk_gitlab_runner-2.3.358.dist-info/METADATA
cdk_gitlab_runner-2.3.358.dist-info/WHEEL
cdk_gitlab_runner-2.3.358.dist-info/top_level.txt
cdk_gitlab_runner-2.3.358.dist-info/RECORD
